pymindmap/__init__.py
pymindmap/__main__.py
pymindmap/app.py
pymindmap/command.py
pymindmap/options.py
pymindmap/urls.py
pymindmap/api/__init__.py
pymindmap/api/folder.py
pymindmap/api/index.py
pymindmap/api/minder.py
pymindmap/api/picture.py
pymindmap/frontend/dist/favicon.ico
pymindmap/frontend/dist/index.html
pymindmap/frontend/dist/kityminder.editor.css
pymindmap/frontend/dist/kityminder.editor.css.map
pymindmap/frontend/dist/kityminder.editor.js
pymindmap/frontend/dist/kityminder.editor.min.css
pymindmap/frontend/dist/kityminder.editor.min.js
pymindmap/frontend/dist/fonts/glyphicons-halflings-regular.eot
pymindmap/frontend/dist/fonts/glyphicons-halflings-regular.svg
pymindmap/frontend/dist/fonts/glyphicons-halflings-regular.ttf
pymindmap/frontend/dist/fonts/glyphicons-halflings-regular.woff
pymindmap/frontend/dist/fonts/glyphicons-halflings-regular.woff2
pymindmap/frontend/dist/images/iconpriority.png
pymindmap/frontend/dist/images/iconprogress.png
pymindmap/frontend/dist/images/icons.png
pymindmap/frontend/dist/images/template.png
pymindmap/frontend/dist/web/angular-ui-router.min.js
pymindmap/frontend/dist/web/angular-ui-tree.min.css
pymindmap/frontend/dist/web/angular-ui-tree.min.js
pymindmap/frontend/dist/web/angular-websocket.min.js
pymindmap/frontend/dist/web/angular.min.js
pymindmap/frontend/dist/web/bootstrap.min.css
pymindmap/frontend/dist/web/codemirror.min.css
pymindmap/frontend/dist/web/codemirror.min.js
pymindmap/frontend/dist/web/color-picker.css
pymindmap/frontend/dist/web/color-picker.js
pymindmap/frontend/dist/web/comment.js
pymindmap/frontend/dist/web/diy.js
pymindmap/frontend/dist/web/hammer.min.js
pymindmap/frontend/dist/web/hotbox.css
pymindmap/frontend/dist/web/hotbox.min.js
pymindmap/frontend/dist/web/jquery.min.js
pymindmap/frontend/dist/web/kity.min.js
pymindmap/frontend/dist/web/kityminder.core.css
pymindmap/frontend/dist/web/kityminder.core.min.js
pymindmap/frontend/dist/web/lodash.min.js
pymindmap/frontend/dist/web/marked.min.js
pymindmap-1.0.22.dist-info/METADATA
pymindmap-1.0.22.dist-info/WHEEL
pymindmap-1.0.22.dist-info/entry_points.txt
pymindmap-1.0.22.dist-info/top_level.txt
pymindmap-1.0.22.dist-info/RECORD
