Metadata-Version: 2.1
Name: pymindmap
Version: 1.0.22
Summary: Python Mindmap
Home-page: https://github.com/lalz001/pymindmap
Author: lalz
Author-email: lfz163453@163.com
License: BSD
Platform: UNKNOWN
Classifier: Development Status :: 4 - Beta
Classifier: Intended Audience :: Developers
Classifier: License :: OSI Approved :: BSD License
Classifier: Topic :: System :: Distributed Computing
Classifier: Programming Language :: Python
Classifier: Programming Language :: Python :: 2
Classifier: Programming Language :: Python :: 2.7
Classifier: Programming Language :: Python :: 3
Classifier: Programming Language :: Python :: 3.3
Classifier: Programming Language :: Python :: 3.4
Classifier: Programming Language :: Python :: 3.5
Classifier: Programming Language :: Python :: 3.6
Classifier: Programming Language :: Python :: 3.7
Classifier: Programming Language :: Python :: Implementation :: CPython
Classifier: Programming Language :: Python :: Implementation :: PyPy
Classifier: Operating System :: OS Independent
Requires-Dist: chardet
Requires-Dist: tornado (<6.0.0,>=5.0.0) ; python_version < "3.5.2"
Requires-Dist: futures ; python_version == "2.7"
Requires-Dist: tornado (<7.0.0,>=5.0.0) ; python_version >= "3.5.2"
